Metadata-Version: 1.0
Name: mopyx-pyside2
Version: 1.0.0
Summary: mopyx_pyside2
Home-page: UNKNOWN
Author: Bogdan Mustiata
Author-email: bogdan.mustiata@gmail.com
License: BSD
Platform: UNKNOWN
